pywhatcms/__init__.py
pywhatcms/pywhatcms.py
pywhatcms-1.0.7.dist-info/LICENSE
pywhatcms-1.0.7.dist-info/METADATA
pywhatcms-1.0.7.dist-info/WHEEL
pywhatcms-1.0.7.dist-info/top_level.txt
pywhatcms-1.0.7.dist-info/RECORD
