Metadata-Version: 2.1
Name: pywhatcms
Version: 1.0.7
Summary: Unofficial WhatCMS API package
Home-page: https://github.com/HA71/pywhatcms
Author: HATI
Author-email: bisha@protonmail.com
License: UNKNOWN
Platform: UNKNOWN
Classifier: Programming Language :: Python :: 3.7
Classifier: Operating System :: OS Independent
Requires-Dist: requests
